Metadata-Version: 2.1
Name: lightrayrider
Version: 2.0.6
Summary: Ray Tracing Monte Carlo photon propagator and column density calculator
Author: Johannes Buchner
Author-email: Johannes Buchner <buchner.johannes@gmx.at>
License:                     GNU AFFERO GENERAL PUBLIC LICENSE
Project-URL: Repository, https://github.com/JohannesBuchner/LightRayRider
Project-URL: Homepage, https://github.com/JohannesBuchner/LightRayRider
Classifier: License :: OSI Approved :: BSD License
Classifier: Programming Language :: Python :: 3
Classifier: Intended Audience :: Developers
Classifier: Intended Audience :: Science/Research
Classifier: Topic :: Scientific/Engineering :: Physics
Classifier: Topic :: Scientific/Engineering :: Astronomy
Classifier: Development Status :: 6 - Mature
Requires-Python: >=3.8
License-File: LICENSE
